c4counter/__init__.py
c4counter/_c4counter.py
c4counter/minimapcut.py
c4counter/paf.py
c4counter/data/C4A.fa
c4counter-0.0.2.dist-info/LICENSE
c4counter-0.0.2.dist-info/METADATA
c4counter-0.0.2.dist-info/WHEEL
c4counter-0.0.2.dist-info/entry_points.txt
c4counter-0.0.2.dist-info/top_level.txt
c4counter-0.0.2.dist-info/RECORD
