Metadata-Version: 2.1
Name: c4counter
Version: 0.0.2
Summary: finds the number and types of complement component 4 (C4) genes in a fasta file. minimap2 is used for mapping
Home-page: https://github.com/irunonayran/c4counter.git
Author: Stephan Scholz
Author-email: stephan.scholz@hhu.de
Project-URL: Bug Tracker, https://github.com/irunonayran/c4counter/issues
Classifier: Programming Language :: Python :: 3
Classifier: License :: OSI Approved :: MIT License
Classifier: Operating System :: OS Independent
Requires-Python: >=3.6
License-File: LICENSE
Requires-Dist: docopt
Requires-Dist: Bio
